bioimageio/core/__init__.py
bioimageio/core/__main__.py
bioimageio/core/_magic_tensor_ops.py
bioimageio/core/_op_base.py
bioimageio/core/_prediction_pipeline.py
bioimageio/core/_resource_tests.py
bioimageio/core/_settings.py
bioimageio/core/axis.py
bioimageio/core/block.py
bioimageio/core/block_meta.py
bioimageio/core/cli.py
bioimageio/core/commands.py
bioimageio/core/common.py
bioimageio/core/dataset.py
bioimageio/core/digest_spec.py
bioimageio/core/io.py
bioimageio/core/model_adapters.py
bioimageio/core/prediction.py
bioimageio/core/proc_ops.py
bioimageio/core/proc_setup.py
bioimageio/core/py.typed
bioimageio/core/sample.py
bioimageio/core/stat_calculators.py
bioimageio/core/stat_measures.py
bioimageio/core/tensor.py
bioimageio/core/backends/__init__.py
bioimageio/core/backends/_model_adapter.py
bioimageio/core/backends/keras_backend.py
bioimageio/core/backends/onnx_backend.py
bioimageio/core/backends/pytorch_backend.py
bioimageio/core/backends/tensorflow_backend.py
bioimageio/core/backends/torchscript_backend.py
bioimageio/core/utils/__init__.py
bioimageio/core/utils/_compare.py
bioimageio/core/utils/_type_guards.py
bioimageio/core/weight_converters/__init__.py
bioimageio/core/weight_converters/_add_weights.py
bioimageio/core/weight_converters/_utils_torch_onnx.py
bioimageio/core/weight_converters/keras_to_tensorflow.py
bioimageio/core/weight_converters/pytorch_to_onnx.py
bioimageio/core/weight_converters/pytorch_to_torchscript.py
bioimageio/core/weight_converters/torchscript_to_onnx.py
bioimageio_core-0.9.5.dist-info/licenses/LICENSE
bioimageio_core-0.9.5.dist-info/METADATA
bioimageio_core-0.9.5.dist-info/WHEEL
bioimageio_core-0.9.5.dist-info/entry_points.txt
bioimageio_core-0.9.5.dist-info/top_level.txt
bioimageio_core-0.9.5.dist-info/RECORD
