Metadata-Version: 2.4
Name: bioimageio.core
Version: 0.9.5
Summary: Python specific core utilities for bioimage.io resources (in particular DL models).
Author-email: Fynn Beuttenmüller <thefynnbe@gmail.com>
Project-URL: Bug Reports, https://github.com/bioimage-io/core-bioimage-io-python/issues
Project-URL: Changelog, https://github.com/bioimage-io/core-bioimage-io-python?tab=readme-ov-file#changelog
Project-URL: Documentation, https://bioimage-io.github.io/core-bioimage-io-python/bioimageio/core.html
Project-URL: Source, https://github.com/bioimage-io/core-bioimage-io-python
Classifier: Development Status :: 3 - Alpha
Classifier: Intended Audience :: Developers
Classifier: Intended Audience :: Science/Research
Classifier: Programming Language :: Python :: 3.9
Classifier: Programming Language :: Python :: 3.10
Classifier: Programming Language :: Python :: 3.11
Classifier: Programming Language :: Python :: 3.12
Classifier: Programming Language :: Python :: 3.13
Requires-Python: >=3.9
License-File: LICENSE
Requires-Dist: bioimageio.spec==0.5.6.0
Requires-Dist: h5py
Requires-Dist: imagecodecs
Requires-Dist: imageio>=2.10
Requires-Dist: loguru
Requires-Dist: numpy
Requires-Dist: pydantic-settings<3,>=2.5
Requires-Dist: pydantic<3,>=2.7.0
Requires-Dist: ruyaml
Requires-Dist: scipy
Requires-Dist: tqdm
Requires-Dist: typing-extensions
Requires-Dist: xarray>=2023.01
Provides-Extra: onnx
Requires-Dist: onnxruntime; extra == "onnx"
Requires-Dist: onnxscript; extra == "onnx"
Provides-Extra: pytorch
Requires-Dist: torch<3,>=1.6; extra == "pytorch"
Requires-Dist: torchvision>=0.21; extra == "pytorch"
Requires-Dist: keras<4,>=3.0; extra == "pytorch"
Provides-Extra: tensorflow
Requires-Dist: tensorflow; extra == "tensorflow"
Requires-Dist: keras<4,>=2.15; extra == "tensorflow"
Provides-Extra: partners
Requires-Dist: careamics; extra == "partners"
Provides-Extra: dev
Requires-Dist: cellpose; extra == "dev"
Requires-Dist: crick; extra == "dev"
Requires-Dist: httpx; extra == "dev"
Requires-Dist: jupyter; extra == "dev"
Requires-Dist: keras<4,>=3.0; extra == "dev"
Requires-Dist: matplotlib; extra == "dev"
Requires-Dist: monai; extra == "dev"
Requires-Dist: numpy; extra == "dev"
Requires-Dist: onnx; extra == "dev"
Requires-Dist: onnxruntime; extra == "dev"
Requires-Dist: onnxscript; extra == "dev"
Requires-Dist: packaging>=17.0; extra == "dev"
Requires-Dist: pdoc; extra == "dev"
Requires-Dist: pre-commit; extra == "dev"
Requires-Dist: pyright==1.1.407; extra == "dev"
Requires-Dist: pytest-cov; extra == "dev"
Requires-Dist: pytest; extra == "dev"
Requires-Dist: python-dotenv; extra == "dev"
Requires-Dist: segment-anything; extra == "dev"
Requires-Dist: tensorflow; extra == "dev"
Requires-Dist: timm; extra == "dev"
Requires-Dist: torch<3,>=1.6; extra == "dev"
Requires-Dist: torchvision>=0.21; extra == "dev"
Dynamic: license-file
